tracker_ml/__init__.py
tracker_ml/api.py
tracker_ml/cli.py
tracker_ml/file_ops.py
tracker_ml/tml.py
tracker_ml/tools.py
tracker_ml-0.0.6.dist-info/LICENSE
tracker_ml-0.0.6.dist-info/METADATA
tracker_ml-0.0.6.dist-info/WHEEL
tracker_ml-0.0.6.dist-info/entry_points.txt
tracker_ml-0.0.6.dist-info/top_level.txt
tracker_ml-0.0.6.dist-info/RECORD
