Metadata-Version: 2.1
Name: tracker-ml
Version: 0.0.6
Summary: Machine learning file and parameter version control SDK for www.tracker.ml
Home-page: https://github.com/sage-t/tracker_ml
Author: Sage Thomas
Author-email: sage.thomas@outlook.com
License: UNKNOWN
Download-URL: https://github.com/sage-t/tracker_ml/archive/v0.0.5.tar.gz
Keywords: MACHINE,LEARNING,VERSION,TRACKING,TRACKER
Platform: UNKNOWN
Classifier: Development Status :: 3 - Alpha
Classifier: Programming Language :: Python :: 3
Classifier: Programming Language :: Python :: 3.4
Classifier: Programming Language :: Python :: 3.5
Classifier: Programming Language :: Python :: 3.6
Classifier: License :: OSI Approved :: MIT License
Classifier: Operating System :: OS Independent
Classifier: Intended Audience :: Developers
Requires-Dist: click
